{
    "dataList": [
      {
        "id": 1090701,
        "levelList": [
          {
            "level": 1,
            "name": "Озари пустоту свою",
            "desc": "Получает (Откровение х 3% от максимальных ОЗ) щита, если этот навык был кинут в Сброс",
            "coinlist": [
                {},
                {},
                {
                  "coindescs": [
                    {
                      "desc": "[OnSucceedAttack] Понижает границу выносливости грешницы на 5"
                    }
                  ]
                }
            ]
          },
          {
            "level": 2,
            "name": "Озари пустоту свою",
            "desc": "Получает (Откровение х 4% от максимальных ОЗ) щита, если этот навык был кинут в Сброс\n[WhenUse] Если Откровений 2 и больше, получает силу монеты, равную (Откровение - 1)",
            "coinlist": [
                {},
                {},
                {
                  "coindescs": [
                    {
                      "desc": "[OnSucceedAttack] Понижает границу выносливости грешницы на 8"
                    }
                  ]
                }
            ]
          },
          {
            "level": 4,
            "name": "Озари пустоту свою",
            "desc": "Получает (Откровение х 5% от максимальных ОЗ) щита, если этот навык был кинут в Сброс\n[WhenUse] Если Откровений 2 и больше, получает силу монеты, равную (Откровение - 1)",
            "coinlist": [
                {},
                {},
                {
                  "coindescs": [
                    {
                      "desc": "[OnSucceedAttack] Понижает границу выносливости грешницы на 10"
                    }
                  ]
                }
            ]
          }
        ]
      },
      {
        "id": 1090702,
        "levelList": [
          {
            "level": 1,
            "name": "Тяжесть знаний",
            "desc": "Получает (Откровение х 5% от максимальных ОЗ) щита, если этот навык был кинут в Сброс\n[WhenUse] Кидает в Сброс умение низшего ранга во всех слотах умений грешницы\n[WhenUse] Получает +2 Провокация на этот слот на следующий ход",
            "coinlist": [
                {},
                {},
                {},
                {
                  "coindescs": [
                    {
                      "desc": "[OnSucceedAttack] Наносит 2 Утопание"
                    }
                  ]
                }
              ]
          },
          {
            "level": 2,
            "name": "Тяжесть знаний",
            "desc": "Получает (Откровение х 8% от максимальных ОЗ) щита, если этот навык был кинут в Сброс\n[WhenUse] Кидает в Сброс умение низшего ранга во всех слотах умений грешницы\n[WhenUse] Получает +3 Провокация на этот слот на следующий ход",
            "coinlist": [
                {},
                {},
                {},
                {
                  "coindescs": [
                    {
                      "desc": "[OnSucceedAttack] Наносит 3 Утопание"
                    }
                  ]
                }
              ]
          },
          {
            "level": 4,
            "name": "Тяжесть знаний",
            "desc": "Получает (Откровение х 10% от максимальных ОЗ) щита, если этот навык был кинут в Сброс\n[WhenUse] Кидает в Сброс умение низшего ранга во всех слотах умений грешницы\n[WhenUse] Получает +5 Провокация на этот слот на следующий ход\n[WhenUse] Если на цели 5+ Утопание, сила столкновения +2",
            "coinlist": [
                {},
                {},
                {},
                {
                  "coindescs": [
                    {
                      "desc": "[OnSucceedAttack] Наносит 5 Утопание"
                    }
                  ]
                }
              ]
          }
        ]
      },
      {
        "id": 1090703,
        "levelList": [
          {
            "level": 3,
            "name": "Болезненное просвещение",
            "desc": "Получает (Откровение х 15% от максимальных ОЗ) щита, если этот навык был кинут в Сброс\n[WhenUse] Кидает в Сброс 2 умения низшего ранга во всех слотах умений грешницы\n[WhenUse] Получает +3 Провокация на этот слот на следующий ход",
            "coinlist": [
              {
                "coindescs": [
                  {
                    "desc": "[OnSucceedAttackHead] Наносит +4 счётчика Утопание"
                  }
                ]
              },
              {},
              {},
              {
                "coindescs": [
                  {
                    "desc": "[OnSucceedAttack] Наносит +2 счётчика Утопание"
                  }
                ]
              }
            ]
          },
          {
            "level": 4,
            "name": "Болезненное просвещение",
            "desc": "Получает (Откровение х 20% от максимальных ОЗ) щита, если этот навык был кинут в Сброс\n[WhenUse] Кидает в Сброс 2 умения низшего ранга во всех слотах умений грешницы\n[WhenUse] Получает +5 Провокация на этот слот на следующий ход\n[WhenUse] Если на цели 7+ Утопание, сила монет +1",
            "coinlist": [
              {
                "coindescs": [
                  {
                    "desc": "[OnSucceedAttackHead] Наносит +4 счётчика Утопание"
                  }
                ]
              },
              {},
              {},
              {
                "coindescs": [
                  {
                    "desc": "[OnSucceedAttack] Наносит +2 счётчика Утопание"
                  }
                ]
              }
            ]
          }
        ]
      },
      {
        "id": 1090704,
        "levelList": [
          {
            "level": 1,
            "name": "Погружённость в познания",
            "desc": "[WhenUse] Кидает в Сброс умение высшего ранга во всех слотах умений грешницы\n[WhenUse] Получает +2 Провокация на этот слот на следующий ход",
            "coinlist": [
              {}
            ]
          },
          {
            "level": 4,
            "name": "Погружённость в познания",
            "desc": "[WhenUse] Кидает в Сброс умение высшего ранга во всех слотах умений грешницы\n[WhenUse] Получает +5 Провокация на этот слот на следующий ход",
            "coinlist": [
              {}
            ]
          }
        ]
      }
    ]
  }